# Source_Files/Lua/lopcodes.h

## File Purpose

Defines the Lua virtual machine instruction format, opcodes, and helper macros for encoding/decoding instructions. This header specifies how VM instructions are laid out in memory and provides compile-time macros to manipulate instruction fields.

## Core Responsibilities

- Define instruction bit layout (opcode, A, B, C arguments and their positions)
- Enumerate all Lua VM opcodes (OP_MOVE, OP_CALL, OP_RETURN, etc.)
- Provide macros to extract/insert instruction fields (GET_OPCODE, GETARG_A, etc.)
- Define instruction creation macros (CREATE_ABC, CREATE_ABx)
- Manage RK indices (constant/register disambiguation via BITRK flag)
- Define opcode argument modes and property queries
- Calculate argument limits (MAXARG_A, MAXARG_B, MAXARG_C, MAXARG_Bx, MAXARG_sBx)

## Key Types / Data Structures

| Name | Kind | Purpose |
|------|------|---------|
| `Instruction` | typedef | 32-bit unsigned type for VM instructions (from llimits.h) |
| `OpMode` | enum | Instruction format type: iABC, iABx, iAsBx |
| `OpCode` | enum | All 37 Lua VM opcodes (MOVE, LOADK, ADD, CALL, RETURN, etc.) |
| `OpArgMask` | enum | Argument mode: OpArgN (unused), OpArgU (used), OpArgR (register), OpArgK (constant/register) |

## Global / File-Static State

| Name | Type | Scope | Purpose |
|------|------|-------|---------|
| `luaP_opmodes` | `const lu_byte[]` | external (defined elsewhere) | Instruction property bitmasks for each opcode (format, arg modes, flags) |
| `luaP_opnames` | `const char*[]` | external (defined elsewhere) | String names of opcodes for debugging/disassembly |

## Key Functions / Methods

All opcodes are defined as an enum with inline documentation. Key macro helpers:

**Instruction Field Extraction:**
- `GET_OPCODE(i)`, `GETARG_A(i)`, `GETARG_B(i)`, `GETARG_C(i)`, `GETARG_Bx(i)`, `GETARG_sBx(i)`
  - Extract opcode and arguments from instruction via bit shifting and masking
  
**Instruction Field Insertion:**
- `SET_OPCODE(i,o)`, `SETARG_A(i,u)`, `SETARG_B(i,b)`, `SETARG_C(i,b)`, `SETARG_Bx(i,b)`, `SETARG_sBx(i,b)`
  - Modify opcode/arguments in instruction using mask-clear-and-or pattern

**Instruction Creation:**
- `CREATE_ABC(o,a,b,c)` ΓÇô assemble instruction from opcode and 3 arguments
- `CREATE_ABx(o,a,bc)` ΓÇô assemble instruction from opcode, A arg, and 18-bit Bx arg

**RK (Register/Constant) Index Helpers:**
- `ISK(x)` ΓÇô test if index refers to a constant (checks BITRK flag)
- `INDEXK(r)` ΓÇô extract constant index from RK value
- `RKASK(x)` ΓÇô encode constant index as RK value

**Opcode Property Queries:**
- `getOpMode(m)` ΓÇô query instruction format (iABC/iABx/iAsBx)
- `getBMode(m)`, `getCMode(m)` ΓÇô query argument modes for B and C fields
- `testAMode(m)`, `testTMode(m)` ΓÇô test if opcode sets A register or is a test instruction

## Control Flow Notes

This header is purely structural/compile-time; it defines no control flow. Used by Lua VM instruction decoder/encoder modules to interpret bytecode instructions. The 37 opcodes span:
- **Data movement**: MOVE, LOADK, LOADBOOL, LOADNIL, GETUPVAL, GETGLOBAL, GETTABLE, etc.
- **Operators**: ADD, SUB, MUL, DIV, MOD, POW, UNM, NOT, LEN, CONCAT
- **Comparisons**: EQ, LT, LE, TEST, TESTSET
- **Control flow**: JMP, CALL, TAILCALL, RETURN, FORLOOP, FORPREP, TFORLOOP
- **Table/closure**: NEWTABLE, SETLIST, CLOSURE
- **Stack management**: CLOSE, VARARG

## External Dependencies

- **config.h** ΓÇô `HAVE_LUA` guard
- **llimits.h** ΓÇô `Instruction` typedef, `MAX_INT`, `cast()` macro, `lu_byte`, `lu_int32`
- **lua.h** (included transitively) ΓÇô Lua API definitions
